{
  "nightly": {
    "description": "Every commit to develop",
    "hide": false,
    "last_updated": "2024-07-08T06:22:05.000Z",
    "last_updated_url": "https://github.com/engels74/sabnzbd/actions/runs/9834492234",
    "latest": false,
    "tags": [
      "nightly",
      "nightly-74daa15ce448dae0b48b753ca49263670ee8efb3",
      "nightly-7ec6bb4"
    ]
  },
  "release": {
    "description": "Releases",
    "hide": false,
    "last_updated": "2024-06-20T19:27:27.000Z",
    "last_updated_url": "https://github.com/engels74/sabnzbd/actions/runs/9602999108",
    "latest": true,
    "tags": [
      "release",
      "release-4.3.2",
      "release-0e9b9f2"
    ]
  },
  "testing": {
    "description": "Pre-releases",
    "hide": false,
    "last_updated": "2024-06-20T19:27:28.000Z",
    "last_updated_url": "https://github.com/engels74/sabnzbd/actions/runs/9602999786",
    "latest": false,
    "tags": [
      "testing",
      "testing-4.3.2",
      "testing-39f8b84"
    ]
  }
}
